[
  {
    "id": 1,
    "first": "Dustin",
    "last": "Irving",
    "department": "Information Technology",
    "position": "Senior Web Developer"
  },
  {
    "id": 2,
    "first": "Rodney",
    "last": "Green",
    "department": "Information Technology",
    "position": "Junior Web Developer"
  },
  {
    "id": 3,
    "first": "Mia",
    "last": "Byeon",
    "department": "Finance",
    "position": "Accountant"
  },
  {
    "id": 4,
    "first": "Oli",
    "last": "Zhao",
    "department": "Engineering",
    "position": "Lead Engineer"
  }
]
